bayfile_uploader/__init__.py
bayfile_uploader/uploader.py
bayfile_uploader-1.1.3.dist-info/LICENSE
bayfile_uploader-1.1.3.dist-info/METADATA
bayfile_uploader-1.1.3.dist-info/WHEEL
bayfile_uploader-1.1.3.dist-info/entry_points.txt
bayfile_uploader-1.1.3.dist-info/top_level.txt
bayfile_uploader-1.1.3.dist-info/RECORD
