Metadata-Version: 2.1
Name: bayfile-uploader
Version: 1.1.3
Summary: File Uploader, uploads files to bayfiles.com
Home-page: https://github.com/roymanigley/bayfile-uploader
Author: Roy Manigley
Author-email: roy.manigley@gmail.com
License: MIT
Platform: UNKNOWN
Classifier: Development Status :: 1 - Planning
Classifier: Intended Audience :: Science/Research
Classifier: License :: OSI Approved :: MIT License
Classifier: Operating System :: POSIX :: Linux
Classifier: Programming Language :: Python :: 3.10
License-File: LICENSE
Requires-Dist: click (>=8.1.3)
Requires-Dist: requests (>=2.28.1)
